RethinkPool-0.4.1.dist-info/DESCRIPTION.rst
RethinkPool-0.4.1.dist-info/METADATA
RethinkPool-0.4.1.dist-info/RECORD
RethinkPool-0.4.1.dist-info/WHEEL
RethinkPool-0.4.1.dist-info/metadata.json
RethinkPool-0.4.1.dist-info/top_level.txt
rethinkpool/__init__.py
