Metadata-Version: 2.0
Name: RethinkPool
Version: 0.4.1
Summary: RethinkDB Connection Pool for Python
Home-page: https://github.com/lucidfrontier45/RethinkPool
Author: Shiqiao Du
Author-email: lucidfrontier.45@gmail.com
License: Apache License v2
Platform: UNKNOWN
Requires-Dist: future
Requires-Dist: rethinkdb
